sentiment_model/__init__.py
sentiment_model/model.py
sentiment_model/predict.py
sentiment_model/train_model.py
sentiment_model/config/__init__.py
sentiment_model/config/core.py
sentiment_model/datasets/__init__.py
sentiment_model/processing/__init__.py
sentiment_model/processing/data_manager.py
sentiment_model/processing/features.py
sentiment_model/processing/validation.py
sentiment_model/trained_models/__init__.py
sentiment_model/trained_tokenizer/__init__.py
aimlops_sentiment_model-0.0.2.dist-info/METADATA
aimlops_sentiment_model-0.0.2.dist-info/WHEEL
aimlops_sentiment_model-0.0.2.dist-info/top_level.txt
aimlops_sentiment_model-0.0.2.dist-info/RECORD
